<?xml version="1.0" encoding="UTF-8"?>
<Document xmlns:xsi="http://www.w3.org/2001/XMLSchema-instance" xmlns="urn:iso:std:iso:20022:tech:xsd:pain.001.001.03">
 <GrpHdr>
  <MsgId>MESSAGEID20200529205116</MsgId>
  <CreDtTm>2020-05-29T20:51:16</CreDtTm>
  <NbOfTxs>4</NbOfTxs>
  <CtrlSum>612,340</CtrlSum>
  <InitgPty>
   <Nm>POSTEFINANCES</Nm>
  </InitgPty>
 </GrpHdr>
 <PmtInf>
  <PmtInfId>BATCHIDID202005292051161</PmtInfId>
  <PmtMtd>TRF</PmtMtd>
  <NbOfTxs>1</NbOfTxs>
  <CtrlSum>126,561</CtrlSum>
  <PmtTpInf>
   <InstrPrty>NORM</InstrPrty>
   <SvcLvl>
    <Cd>ACH</Cd>
   </SvcLvl>
   <LclInstrm>
    <Cd>CCI</Cd>
   </LclInstrm>
   <CtgyPurp>
    <Cd>SUPP</Cd>
   </CtgyPurp>
  </PmtTpInf>
  <ReqdExctnDt>2020-05-29</ReqdExctnDt>
  <Dbtr>
   <Nm>DIRECTION FINANCES et COMPTABILITE POSTE</Nm>
  </Dbtr>
  <DbtrAcct>
   <Id>
    <Othr>
     <Id>000034260010</Id>
    </Othr>
    <SchmeNm>
     <Cd>BBAN</Cd>
    </SchmeNm>
    <Issr>COMPTE POSTEFINANCES DEBITE</Issr>
   </Id>
  </DbtrAcct>
 </PmtInf>
 <DbtrAgt>
  <FinInstnId>
   <BIC>OSTSND1000</BIC>
  </FinInstnId>
 </DbtrAgt>
 <CdtTrfTxInf>
  <PmtId>
   <InstrId>INSTRID201912131040000059</InstrId>
   <EndToEndId>E2EID201912131040000059</EndToEndId>
  </PmtId>
  <Amt Ccy="XOF">
   <InstdAmt>126,561</InstdAmt>
  </Amt>
  <ChrgBr>SLEV</ChrgBr>
  <CdtrAgt>
   <FinInstnId>
    <BIC>POSTSND1000</BIC>
   </FinInstnId>
  </CdtrAgt>
  <Cbtr>
   <Nm>FATOUMATA  BITEYE</Nm>
  </Cbtr>
  <CdtrAcct>
   <Id>
    <IBAN>SN1000100500295396000512</IBAN>
   </Id>
  </CdtrAcct>
  <Purp>
   <Cd>BEXP</Cd>
  </Purp>
 </CdtTrfTxInf>
 <PmtInf>
  <PmtInfId>BATCHIDID202005292051162</PmtInfId>
  <PmtMtd>TRF</PmtMtd>
  <NbOfTxs>2</NbOfTxs>
  <CtrlSum>146,025</CtrlSum>
  <PmtTpInf>
   <InstrPrty>NORM</InstrPrty>
   <SvcLvl>
    <Cd>ACH</Cd>
   </SvcLvl>
   <LclInstrm>
    <Cd>CCI</Cd>
   </LclInstrm>
   <CtgyPurp>
    <Cd>SUPP</Cd>
   </CtgyPurp>
  </PmtTpInf>
  <ReqdExctnDt>2020-05-29</ReqdExctnDt>
  <Dbtr>
   <Nm>DIRECTION FINANCES et COMPTABILITE POSTE</Nm>
  </Dbtr>
  <DbtrAcct>
   <Id>
    <Othr>
     <Id>000034260010</Id>
    </Othr>
    <SchmeNm>
     <Cd>BBAN</Cd>
    </SchmeNm>
    <Issr>COMPTE POSTEFINANCES DEBITE</Issr>
   </Id>
  </DbtrAcct>
 </PmtInf>
 <DbtrAgt>
  <FinInstnId>
   <BIC>OSTSND1000</BIC>
  </FinInstnId>
 </DbtrAgt>
 <CdtTrfTxInf>
  <PmtId>
   <InstrId>INSTRID201912131040000059</InstrId>
   <EndToEndId>E2EID201912131040000059</EndToEndId>
  </PmtId>
  <Amt Ccy="XOF">
   <InstdAmt>146,025</InstdAmt>
  </Amt>
  <ChrgBr>SLEV</ChrgBr>
  <CdtrAgt>
   <FinInstnId>
    <BIC>POSTSND1000</BIC>
   </FinInstnId>
  </CdtrAgt>
  <Cbtr>
   <Nm>SOULEYMANE  TRAORE</Nm>
  </Cbtr>
  <CdtrAcct>
   <Id>
    <IBAN>SN1000100400279595000586</IBAN>
   </Id>
  </CdtrAcct>
  <Purp>
   <Cd>BEXP</Cd>
  </Purp>
 </CdtTrfTxInf>
 <PmtInf>
  <PmtInfId>BATCHIDID202005292051163</PmtInfId>
  <PmtMtd>TRF</PmtMtd>
  <NbOfTxs>3</NbOfTxs>
  <CtrlSum>339,754</CtrlSum>
  <PmtTpInf>
   <InstrPrty>NORM</InstrPrty>
   <SvcLvl>
    <Cd>ACH</Cd>
   </SvcLvl>
   <LclInstrm>
    <Cd>CCI</Cd>
   </LclInstrm>
   <CtgyPurp>
    <Cd>SUPP</Cd>
   </CtgyPurp>
  </PmtTpInf>
  <ReqdExctnDt>2020-05-29</ReqdExctnDt>
  <Dbtr>
   <Nm>DIRECTION FINANCES et COMPTABILITE POSTE</Nm>
  </Dbtr>
  <DbtrAcct>
   <Id>
    <Othr>
     <Id>000034260010</Id>
    </Othr>
    <SchmeNm>
     <Cd>BBAN</Cd>
    </SchmeNm>
    <Issr>COMPTE POSTEFINANCES DEBITE</Issr>
   </Id>
  </DbtrAcct>
 </PmtInf>
 <DbtrAgt>
  <FinInstnId>
   <BIC>OSTSND1000</BIC>
  </FinInstnId>
 </DbtrAgt>
 <CdtTrfTxInf>
  <PmtId>
   <InstrId>INSTRID201912131040000059</InstrId>
   <EndToEndId>E2EID201912131040000059</EndToEndId>
  </PmtId>
  <Amt Ccy="XOF">
   <InstdAmt>339,754</InstdAmt>
  </Amt>
  <ChrgBr>SLEV</ChrgBr>
  <CdtrAgt>
   <FinInstnId>
    <BIC>POSTSND1000</BIC>
   </FinInstnId>
  </CdtrAgt>
  <Cbtr>
   <Nm>ISSA  NDIEGUENE</Nm>
  </Cbtr>
  <CdtrAcct>
   <Id>
    <IBAN>SN1000400200947454000297</IBAN>
   </Id>
  </CdtrAcct>
  <Purp>
   <Cd>BEXP</Cd>
  </Purp>
 </CdtTrfTxInf>
 <PmtInf>
  <PmtInfId>BATCHIDID202005292051164</PmtInfId>
  <PmtMtd>TRF</PmtMtd>
  <NbOfTxs>4</NbOfTxs>
  <CtrlSum>0</CtrlSum>
  <PmtTpInf>
   <InstrPrty>NORM</InstrPrty>
   <SvcLvl>
    <Cd>ACH</Cd>
   </SvcLvl>
   <LclInstrm>
    <Cd>CCI</Cd>
   </LclInstrm>
   <CtgyPurp>
    <Cd>SUPP</Cd>
   </CtgyPurp>
  </PmtTpInf>
  <ReqdExctnDt>2020-05-29</ReqdExctnDt>
  <Dbtr>
   <Nm>DIRECTION FINANCES et COMPTABILITE POSTE</Nm>
  </Dbtr>
  <DbtrAcct>
   <Id>
    <Othr>
     <Id></Id>
    </Othr>
    <SchmeNm>
     <Cd>BBAN</Cd>
    </SchmeNm>
    <Issr>COMPTE POSTEFINANCES DEBITE</Issr>
   </Id>
  </DbtrAcct>
 </PmtInf>
 <DbtrAgt>
  <FinInstnId>
   <BIC>OSTSND1000</BIC>
  </FinInstnId>
 </DbtrAgt>
 <CdtTrfTxInf>
  <PmtId>
   <InstrId>INSTRID201912131040000059</InstrId>
   <EndToEndId>E2EID201912131040000059</EndToEndId>
  </PmtId>
  <Amt Ccy="XOF">
   <InstdAmt>0</InstdAmt>
  </Amt>
  <ChrgBr>SLEV</ChrgBr>
  <CdtrAgt>
   <FinInstnId>
    <BIC>POSTSND1000</BIC>
   </FinInstnId>
  </CdtrAgt>
  <Cbtr>
   <Nm></Nm>
  </Cbtr>
  <CdtrAcct>
   <Id>
    <IBAN></IBAN>
   </Id>
  </CdtrAcct>
  <Purp>
   <Cd>BEXP</Cd>
  </Purp>
 </CdtTrfTxInf>
</Document>
